{
  "id": "https://openalex.org/W1975128847",
  "title": "Ecospace: Prediction of Mesoscale Spatial Patterns in Trophic Relationships of Exploited Ecosystems, with Emphasis on the Impacts of Marine Protected Areas",
  "abstract": "No abstract available",
  "authors": [
    {
      "name": "Carl J. Walters"
    },
    {
      "name": "Daniel Pauly"
    },
    {
      "name": "Villy Christensen"
    }
  ],
  "publication_year": 1999,
  "cited_by_count": 390,
  "primary_topic": "Marine and fisheries research",
  "subfield_topic": "Global and Planetary Change",
  "field_topic": "Environmental Science",
  "domain_topic": "Physical Sciences",
  "referenced_works": [
    "https://openalex.org/W146535024",
    "https://openalex.org/W1485469120",
    "https://openalex.org/W1524204919",
    "https://openalex.org/W1524760816",
    "https://openalex.org/W1558742124",
    "https://openalex.org/W1575642081",
    "https://openalex.org/W18775530",
    "https://openalex.org/W1967049079",
    "https://openalex.org/W1968315631",
    "https://openalex.org/W1980101723",
    "https://openalex.org/W1992808937",
    "https://openalex.org/W1999882000",
    "https://openalex.org/W2022523551",
    "https://openalex.org/W2036431711",
    "https://openalex.org/W2040835496",
    "https://openalex.org/W2076153258",
    "https://openalex.org/W2078430711",
    "https://openalex.org/W2079844236",
    "https://openalex.org/W2081050205",
    "https://openalex.org/W2090062393",
    "https://openalex.org/W2091579301",
    "https://openalex.org/W2137705922",
    "https://openalex.org/W2141193773",
    "https://openalex.org/W2165007446",
    "https://openalex.org/W2267071955",
    "https://openalex.org/W2337045272",
    "https://openalex.org/W2603331681",
    "https://openalex.org/W2709573646",
    "https://openalex.org/W2749675060",
    "https://openalex.org/W2901065813",
    "https://openalex.org/W412246939"
  ]
}