{
  "id": "https://openalex.org/W2017468987",
  "title": "Global overview of the applications of the Ecopath with Ecosim modeling approach using the EcoBase models repository",
  "abstract": "No abstract available",
  "authors": [
    {
      "name": "Mathieu Colléter"
    },
    {
      "name": "Audrey Valls"
    },
    {
      "name": "Jérôme Guitton"
    },
    {
      "name": "Didier Gascuel"
    },
    {
      "name": "Daniel Pauly"
    },
    {
      "name": "Villy Christensen"
    }
  ],
  "publication_year": 2015,
  "cited_by_count": 247,
  "primary_topic": "Marine and fisheries research",
  "subfield_topic": "Global and Planetary Change",
  "field_topic": "Environmental Science",
  "domain_topic": "Physical Sciences",
  "referenced_works": [
    "https://openalex.org/W112103770",
    "https://openalex.org/W146535024",
    "https://openalex.org/W1492835558",
    "https://openalex.org/W1524760816",
    "https://openalex.org/W1540760009",
    "https://openalex.org/W1725927130",
    "https://openalex.org/W1749515229",
    "https://openalex.org/W1943895098",
    "https://openalex.org/W1966476930",
    "https://openalex.org/W1967049079",
    "https://openalex.org/W1969102921",
    "https://openalex.org/W1975128847",
    "https://openalex.org/W1978294673",
    "https://openalex.org/W1984192729",
    "https://openalex.org/W1990566709",
    "https://openalex.org/W1991569047",
    "https://openalex.org/W1994756853",
    "https://openalex.org/W2003647390",
    "https://openalex.org/W2010013632",
    "https://openalex.org/W2023671311",
    "https://openalex.org/W2028293789",
    "https://openalex.org/W2033973361",
    "https://openalex.org/W2046766973",
    "https://openalex.org/W2049554549",
    "https://openalex.org/W2070564523",
    "https://openalex.org/W2075082468",
    "https://openalex.org/W2076381052",
    "https://openalex.org/W20787259",
    "https://openalex.org/W2081050205",
    "https://openalex.org/W2096623946",
    "https://openalex.org/W2098249933",
    "https://openalex.org/W2100137827",
    "https://openalex.org/W2103037732",
    "https://openalex.org/W2103943852",
    "https://openalex.org/W2105280308",
    "https://openalex.org/W2111510688",
    "https://openalex.org/W2113534686",
    "https://openalex.org/W2125126374",
    "https://openalex.org/W2130517250",
    "https://openalex.org/W2147775078",
    "https://openalex.org/W2151589195",
    "https://openalex.org/W2154561328",
    "https://openalex.org/W2156689933",
    "https://openalex.org/W2156695268",
    "https://openalex.org/W2157832927",
    "https://openalex.org/W2164306581",
    "https://openalex.org/W2169969573",
    "https://openalex.org/W2182148848",
    "https://openalex.org/W2185752871",
    "https://openalex.org/W2252819758",
    "https://openalex.org/W2346104165",
    "https://openalex.org/W2725811976",
    "https://openalex.org/W2792088475",
    "https://openalex.org/W2970515275",
    "https://openalex.org/W4232313964",
    "https://openalex.org/W564040604"
  ]
}