{
  "id": "https://openalex.org/W2033923701",
  "title": "The future of fish",
  "abstract": "No abstract available",
  "authors": [
    {
      "name": "Boris Worm"
    },
    {
      "name": "Trevor A. Branch"
    }
  ],
  "publication_year": 2012,
  "cited_by_count": 256,
  "primary_topic": "Marine and fisheries research",
  "subfield_topic": "Global and Planetary Change",
  "field_topic": "Environmental Science",
  "domain_topic": "Physical Sciences",
  "referenced_works": [
    "https://openalex.org/W1492835558",
    "https://openalex.org/W1513136390",
    "https://openalex.org/W1573362963",
    "https://openalex.org/W1599305990",
    "https://openalex.org/W1667366711",
    "https://openalex.org/W1836271271",
    "https://openalex.org/W1960744456",
    "https://openalex.org/W1998100494",
    "https://openalex.org/W2004805145",
    "https://openalex.org/W2008465998",
    "https://openalex.org/W2008492531",
    "https://openalex.org/W2008733299",
    "https://openalex.org/W2013438632",
    "https://openalex.org/W2015918764",
    "https://openalex.org/W2020170202",
    "https://openalex.org/W2029579385",
    "https://openalex.org/W2031695825",
    "https://openalex.org/W2032652097",
    "https://openalex.org/W2034329631",
    "https://openalex.org/W2041587880",
    "https://openalex.org/W2054534384",
    "https://openalex.org/W2060397574",
    "https://openalex.org/W2060789210",
    "https://openalex.org/W2061300007",
    "https://openalex.org/W2067804762",
    "https://openalex.org/W2067965812",
    "https://openalex.org/W2068360094",
    "https://openalex.org/W2075388586",
    "https://openalex.org/W2076824706",
    "https://openalex.org/W2081759880",
    "https://openalex.org/W2090684738",
    "https://openalex.org/W2095018223",
    "https://openalex.org/W2098165869",
    "https://openalex.org/W2101459943",
    "https://openalex.org/W2102728331",
    "https://openalex.org/W2108402454",
    "https://openalex.org/W2116093469",
    "https://openalex.org/W2118956924",
    "https://openalex.org/W2123069546",
    "https://openalex.org/W2124565737",
    "https://openalex.org/W2132556874",
    "https://openalex.org/W2132569622",
    "https://openalex.org/W2134036584",
    "https://openalex.org/W2137332005",
    "https://openalex.org/W2140103666",
    "https://openalex.org/W2152474769",
    "https://openalex.org/W2156523992",
    "https://openalex.org/W2156709416",
    "https://openalex.org/W4250459928",
    "https://openalex.org/W576485420",
    "https://openalex.org/W640741398"
  ]
}