{
  "id": "https://openalex.org/W2134151301",
  "title": "Predicting community responses to perturbations in the face of imperfect knowledge and network complexity",
  "abstract": "How best to predict the effects of perturbations to ecological communities has been a long-standing goal for both applied and basic ecology. This quest has recently been revived by new empirical data, new analysis methods, and increased computing speed, with the promise that ecologically important insights may be obtainable from a limited knowledge of community interactions. We use empirically based and simulated networks of varying size and connectance to assess two limitations to predicting perturbation responses in multispecies communities: (1) the inaccuracy by which species interaction strengths are empirically quantified and (2) the indeterminacy of species responses due to indirect effects associated with network size and structure. We find that even modest levels of species richness and connectance (-25 pairwise interactions) impose high requirements for interaction strength estimates because system indeterminacy rapidly overwhelms predictive insights. Nevertheless, even poorly estimated interaction strengths provide greater average predictive certainty than an approach that uses only the sign of each interaction. Our simulations provide guidance in dealing with the trade-offs involved in maximizing the utility of network approaches for predicting dynamics in multispecies communities.",
  "authors": [
    {
      "name": "Márk Novák"
    },
    {
      "name": "J. Timothy Wootton"
    },
    {
      "name": "Daniel F. Doak"
    },
    {
      "name": "Mark Emmerson"
    },
    {
      "name": "James A. Estes"
    },
    {
      "name": "M. Tim Tinker"
    }
  ],
  "publication_year": 2010,
  "cited_by_count": 126,
  "primary_topic": "Evolutionary Game Theory and Cooperation",
  "subfield_topic": "Sociology and Political Science",
  "field_topic": "Social Sciences",
  "domain_topic": "Social Sciences",
  "referenced_works": [
    "https://openalex.org/W135503764",
    "https://openalex.org/W1512279977",
    "https://openalex.org/W1561689556",
    "https://openalex.org/W174594330",
    "https://openalex.org/W1968589214",
    "https://openalex.org/W1972501876",
    "https://openalex.org/W1973199530",
    "https://openalex.org/W1973432171",
    "https://openalex.org/W1975998971",
    "https://openalex.org/W1979067113",
    "https://openalex.org/W1981272107",
    "https://openalex.org/W1981768350",
    "https://openalex.org/W1985381446",
    "https://openalex.org/W1988201445",
    "https://openalex.org/W1989442815",
    "https://openalex.org/W1991560151",
    "https://openalex.org/W1999855446",
    "https://openalex.org/W1999936884",
    "https://openalex.org/W2000256297",
    "https://openalex.org/W2002834368",
    "https://openalex.org/W2004451443",
    "https://openalex.org/W2005590794",
    "https://openalex.org/W2006265485",
    "https://openalex.org/W2009739358",
    "https://openalex.org/W2010307518",
    "https://openalex.org/W2010707998",
    "https://openalex.org/W2015038772",
    "https://openalex.org/W2017841226",
    "https://openalex.org/W2018657850",
    "https://openalex.org/W2026164147",
    "https://openalex.org/W2028555396",
    "https://openalex.org/W2039537049",
    "https://openalex.org/W2040199098",
    "https://openalex.org/W2041858739",
    "https://openalex.org/W2047827879",
    "https://openalex.org/W2049546703",
    "https://openalex.org/W2051827465",
    "https://openalex.org/W2053852032",
    "https://openalex.org/W2055665225",
    "https://openalex.org/W2056297774",
    "https://openalex.org/W2061430939",
    "https://openalex.org/W2062108814",
    "https://openalex.org/W2068349998",
    "https://openalex.org/W2072242172",
    "https://openalex.org/W2077353305",
    "https://openalex.org/W2079032822",
    "https://openalex.org/W2080748515",
    "https://openalex.org/W2082119996",
    "https://openalex.org/W2083503429",
    "https://openalex.org/W2086067408",
    "https://openalex.org/W2091814785",
    "https://openalex.org/W2092295003",
    "https://openalex.org/W2094023494",
    "https://openalex.org/W2097186933",
    "https://openalex.org/W2098637141",
    "https://openalex.org/W2101478043",
    "https://openalex.org/W2106473046",
    "https://openalex.org/W2114518726",
    "https://openalex.org/W2121660347",
    "https://openalex.org/W2127298459",
    "https://openalex.org/W2133573796",
    "https://openalex.org/W2136187322",
    "https://openalex.org/W2149049530",
    "https://openalex.org/W2151402778",
    "https://openalex.org/W2156523992",
    "https://openalex.org/W2158084754",
    "https://openalex.org/W2159694504",
    "https://openalex.org/W2161611531",
    "https://openalex.org/W2165864535",
    "https://openalex.org/W2165976254",
    "https://openalex.org/W2167636310",
    "https://openalex.org/W2577040454",
    "https://openalex.org/W4237315514",
    "https://openalex.org/W93423279"
  ]
}