{
  "id": "https://openalex.org/W2146338434",
  "title": "Status of Biodiversity in the Baltic Sea",
  "abstract": "The brackish Baltic Sea hosts species of various origins and environmental tolerances. These immigrated to the sea 10,000 to 15,000 years ago or have been introduced to the area over the relatively recent history of the system. The Baltic Sea has only one known endemic species. While information on some abiotic parameters extends back as long as five centuries and first quantitative snapshot data on biota (on exploited fish populations) originate generally from the same time, international coordination of research began in the early twentieth century. Continuous, annual Baltic Sea-wide long-term datasets on several organism groups (plankton, benthos, fish) are generally available since the mid-1950s. Based on a variety of available data sources (published papers, reports, grey literature, unpublished data), the Baltic Sea, incl. Kattegat, hosts altogether at least 6,065 species, including at least 1,700 phytoplankton, 442 phytobenthos, at least 1,199 zooplankton, at least 569 meiozoobenthos, 1,476 macrozoobenthos, at least 380 vertebrate parasites, about 200 fish, 3 seal, and 83 bird species. In general, but not in all organism groups, high sub-regional total species richness is associated with elevated salinity. Although in comparison with fully marine areas the Baltic Sea supports fewer species, several facets of the system's diversity remain underexplored to this day, such as micro-organisms, foraminiferans, meiobenthos and parasites. In the future, climate change and its interactions with multiple anthropogenic forcings are likely to have major impacts on the Baltic biodiversity.",
  "authors": [
    {
      "name": "Henn Ojaveer"
    },
    {
      "name": "Andres Jaanus"
    },
    {
      "name": "Brian R. MacKenzie"
    },
    {
      "name": "Georg Martin"
    },
    {
      "name": "Sergej Olenin"
    },
    {
      "name": "Teresa Radziejewska"
    },
    {
      "name": "Irena V. Telesh"
    },
    {
      "name": "Michael L. Zettler"
    },
    {
      "name": "Anastasija Zaiko"
    }
  ],
  "publication_year": 2010,
  "cited_by_count": 339,
  "primary_topic": "Marine and fisheries research",
  "subfield_topic": "Global and Planetary Change",
  "field_topic": "Environmental Science",
  "domain_topic": "Physical Sciences",
  "referenced_works": [
    "https://openalex.org/W1485326812",
    "https://openalex.org/W1492867326",
    "https://openalex.org/W1498867904",
    "https://openalex.org/W1528657455",
    "https://openalex.org/W1543736299",
    "https://openalex.org/W1560251347",
    "https://openalex.org/W1561317629",
    "https://openalex.org/W1572330334",
    "https://openalex.org/W1597712209",
    "https://openalex.org/W1607800566",
    "https://openalex.org/W1772632663",
    "https://openalex.org/W1855158498",
    "https://openalex.org/W1963731700",
    "https://openalex.org/W1980331392",
    "https://openalex.org/W1983783249",
    "https://openalex.org/W1984334147",
    "https://openalex.org/W1984492939",
    "https://openalex.org/W1986355743",
    "https://openalex.org/W1986403698",
    "https://openalex.org/W1988201788",
    "https://openalex.org/W1989536364",
    "https://openalex.org/W1990581570",
    "https://openalex.org/W1994579616",
    "https://openalex.org/W1998634190",
    "https://openalex.org/W1999666074",
    "https://openalex.org/W2001333942",
    "https://openalex.org/W2002038211",
    "https://openalex.org/W2009442825",
    "https://openalex.org/W2010770365",
    "https://openalex.org/W2011907490",
    "https://openalex.org/W2013099879",
    "https://openalex.org/W2013219055",
    "https://openalex.org/W2013510287",
    "https://openalex.org/W2014999214",
    "https://openalex.org/W2016000707",
    "https://openalex.org/W2021874192",
    "https://openalex.org/W2023366931",
    "https://openalex.org/W2031448904",
    "https://openalex.org/W2041546122",
    "https://openalex.org/W2048486154",
    "https://openalex.org/W2050570029",
    "https://openalex.org/W2051513199",
    "https://openalex.org/W2052716833",
    "https://openalex.org/W2062498006",
    "https://openalex.org/W2063341860",
    "https://openalex.org/W2065511339",
    "https://openalex.org/W2070134003",
    "https://openalex.org/W2077989318",
    "https://openalex.org/W2078610275",
    "https://openalex.org/W2080169924",
    "https://openalex.org/W2081414504",
    "https://openalex.org/W2082684619",
    "https://openalex.org/W2088419984",
    "https://openalex.org/W2090089529",
    "https://openalex.org/W2092275207",
    "https://openalex.org/W2093173261",
    "https://openalex.org/W2093855483",
    "https://openalex.org/W2095164768",
    "https://openalex.org/W2096133327",
    "https://openalex.org/W2096294976",
    "https://openalex.org/W2099967344",
    "https://openalex.org/W2100382111",
    "https://openalex.org/W2101909754",
    "https://openalex.org/W2102840436",
    "https://openalex.org/W2103230693",
    "https://openalex.org/W2104590900",
    "https://openalex.org/W2105620701",
    "https://openalex.org/W2108764021",
    "https://openalex.org/W2114654060",
    "https://openalex.org/W2118145480",
    "https://openalex.org/W2120255171",
    "https://openalex.org/W2123490836",
    "https://openalex.org/W2127008241",
    "https://openalex.org/W2127531776",
    "https://openalex.org/W2128092399",
    "https://openalex.org/W2133970842",
    "https://openalex.org/W2134184799",
    "https://openalex.org/W2137921857",
    "https://openalex.org/W2139447558",
    "https://openalex.org/W2140677749",
    "https://openalex.org/W2147780951",
    "https://openalex.org/W2148266369",
    "https://openalex.org/W2149191986",
    "https://openalex.org/W2149500449",
    "https://openalex.org/W2152924509",
    "https://openalex.org/W2157727063",
    "https://openalex.org/W2160923436",
    "https://openalex.org/W2164859398",
    "https://openalex.org/W2165488287",
    "https://openalex.org/W2172803358",
    "https://openalex.org/W2178748253",
    "https://openalex.org/W2180898445",
    "https://openalex.org/W2183852218",
    "https://openalex.org/W2233594168",
    "https://openalex.org/W2264141597",
    "https://openalex.org/W2316249610",
    "https://openalex.org/W240679801",
    "https://openalex.org/W2476431461",
    "https://openalex.org/W2482654005",
    "https://openalex.org/W2484069416",
    "https://openalex.org/W2503057464",
    "https://openalex.org/W2513013402",
    "https://openalex.org/W2575970359",
    "https://openalex.org/W2615180781",
    "https://openalex.org/W2737748176",
    "https://openalex.org/W2741448070",
    "https://openalex.org/W2794900079",
    "https://openalex.org/W286729273",
    "https://openalex.org/W2990517684",
    "https://openalex.org/W2990615080",
    "https://openalex.org/W2995267",
    "https://openalex.org/W3004322205",
    "https://openalex.org/W3105194683",
    "https://openalex.org/W31260010",
    "https://openalex.org/W3208249974",
    "https://openalex.org/W3214667622",
    "https://openalex.org/W345080406",
    "https://openalex.org/W4232131478",
    "https://openalex.org/W4239265141",
    "https://openalex.org/W4239443032",
    "https://openalex.org/W4239528210",
    "https://openalex.org/W4285719527",
    "https://openalex.org/W4312773166",
    "https://openalex.org/W563160546",
    "https://openalex.org/W578441165",
    "https://openalex.org/W580300213",
    "https://openalex.org/W600586755",
    "https://openalex.org/W610959992",
    "https://openalex.org/W630894602",
    "https://openalex.org/W639875775",
    "https://openalex.org/W652035363",
    "https://openalex.org/W75486069",
    "https://openalex.org/W768166939",
    "https://openalex.org/W823108989",
    "https://openalex.org/W83689810"
  ]
}