{
  "id": "https://openalex.org/W2140853384",
  "title": "Ecosystem services",
  "abstract": "Across the world, governments, NGOs, scientists, policy-makers, and resource managers are learning to speak in the language of ecosystem services. It is a concept that seems to belong to what many geographers call neoliberal-style environmental policies. However, the policies and practices around the ecosystem service concept deviate considerably from neoliberal doctrine. Our primary aim is to open up space for informed conversation about ecosystem services in geography by exploring the internal heterogeneity and tensions within the world of ecosystem service policies. In describing these debates on their own terms, we find a diverse and wide-ranging set of actors and viewpoints.",
  "authors": [
    {
      "name": "Jessica Dempsey"
    },
    {
      "name": "Morgan Robertson"
    }
  ],
  "publication_year": 2012,
  "cited_by_count": 233,
  "primary_topic": "Land Use and Ecosystem Services",
  "subfield_topic": "Global and Planetary Change",
  "field_topic": "Environmental Science",
  "domain_topic": "Physical Sciences",
  "referenced_works": [
    "https://openalex.org/W1480313761",
    "https://openalex.org/W1497801447",
    "https://openalex.org/W1501623998",
    "https://openalex.org/W1523079103",
    "https://openalex.org/W1543740732",
    "https://openalex.org/W1547237219",
    "https://openalex.org/W1559400250",
    "https://openalex.org/W1594416166",
    "https://openalex.org/W1605562776",
    "https://openalex.org/W176498584",
    "https://openalex.org/W1814272073",
    "https://openalex.org/W1905536488",
    "https://openalex.org/W1915524933",
    "https://openalex.org/W1938705862",
    "https://openalex.org/W1947283864",
    "https://openalex.org/W1967846188",
    "https://openalex.org/W1968401264",
    "https://openalex.org/W1971596564",
    "https://openalex.org/W1973505912",
    "https://openalex.org/W1981105241",
    "https://openalex.org/W1982053377",
    "https://openalex.org/W1983456093",
    "https://openalex.org/W1983962627",
    "https://openalex.org/W1991422542",
    "https://openalex.org/W1991538680",
    "https://openalex.org/W1994122124",
    "https://openalex.org/W1994734333",
    "https://openalex.org/W1997119179",
    "https://openalex.org/W2001161477",
    "https://openalex.org/W2003242061",
    "https://openalex.org/W2003605835",
    "https://openalex.org/W2006243840",
    "https://openalex.org/W2013811158",
    "https://openalex.org/W2016940303",
    "https://openalex.org/W2019045583",
    "https://openalex.org/W2019291839",
    "https://openalex.org/W2023740039",
    "https://openalex.org/W2026055193",
    "https://openalex.org/W2026834311",
    "https://openalex.org/W2026848533",
    "https://openalex.org/W2027075769",
    "https://openalex.org/W2035673872",
    "https://openalex.org/W2037845267",
    "https://openalex.org/W2038163849",
    "https://openalex.org/W2041082080",
    "https://openalex.org/W2041207891",
    "https://openalex.org/W2045757483",
    "https://openalex.org/W2046109790",
    "https://openalex.org/W2050625475",
    "https://openalex.org/W2051058668",
    "https://openalex.org/W2051211133",
    "https://openalex.org/W2051926647",
    "https://openalex.org/W2056461792",
    "https://openalex.org/W2056614018",
    "https://openalex.org/W2057931959",
    "https://openalex.org/W2058932559",
    "https://openalex.org/W2060437728",
    "https://openalex.org/W2064519090",
    "https://openalex.org/W2066246263",
    "https://openalex.org/W2066677532",
    "https://openalex.org/W2070436391",
    "https://openalex.org/W2073831590",
    "https://openalex.org/W2074600421",
    "https://openalex.org/W2075842218",
    "https://openalex.org/W2077742508",
    "https://openalex.org/W2078941804",
    "https://openalex.org/W2081641428",
    "https://openalex.org/W2082252945",
    "https://openalex.org/W2082479717",
    "https://openalex.org/W2085425015",
    "https://openalex.org/W2085997333",
    "https://openalex.org/W2086498757",
    "https://openalex.org/W2087320447",
    "https://openalex.org/W2095900657",
    "https://openalex.org/W2096885696",
    "https://openalex.org/W2103975681",
    "https://openalex.org/W2108173127",
    "https://openalex.org/W2115893469",
    "https://openalex.org/W2117386630",
    "https://openalex.org/W2118615918",
    "https://openalex.org/W2119119035",
    "https://openalex.org/W2119487893",
    "https://openalex.org/W2123071655",
    "https://openalex.org/W2124350766",
    "https://openalex.org/W2127085433",
    "https://openalex.org/W2127604964",
    "https://openalex.org/W2132890679",
    "https://openalex.org/W2136986485",
    "https://openalex.org/W2138603521",
    "https://openalex.org/W2141839736",
    "https://openalex.org/W2152330821",
    "https://openalex.org/W2152643012",
    "https://openalex.org/W2153303091",
    "https://openalex.org/W2153509701",
    "https://openalex.org/W2156016952",
    "https://openalex.org/W2157805396",
    "https://openalex.org/W2159969226",
    "https://openalex.org/W2161809738",
    "https://openalex.org/W2162164606",
    "https://openalex.org/W2166402853",
    "https://openalex.org/W2167549568",
    "https://openalex.org/W2171067728",
    "https://openalex.org/W2172268965",
    "https://openalex.org/W2259190649",
    "https://openalex.org/W2314472206",
    "https://openalex.org/W2324107804",
    "https://openalex.org/W2613902989",
    "https://openalex.org/W2746485780",
    "https://openalex.org/W2798568231",
    "https://openalex.org/W2900158462",
    "https://openalex.org/W2913163892",
    "https://openalex.org/W2986234434",
    "https://openalex.org/W3013984851",
    "https://openalex.org/W3124530973",
    "https://openalex.org/W3124677426",
    "https://openalex.org/W319842024",
    "https://openalex.org/W4211137595",
    "https://openalex.org/W4233116865",
    "https://openalex.org/W4241852105",
    "https://openalex.org/W4242874144",
    "https://openalex.org/W4244854298",
    "https://openalex.org/W4245727312",
    "https://openalex.org/W4246075500",
    "https://openalex.org/W4247390218",
    "https://openalex.org/W4252099179",
    "https://openalex.org/W4301267015",
    "https://openalex.org/W4387873658",
    "https://openalex.org/W569690224",
    "https://openalex.org/W615321509",
    "https://openalex.org/W648175835",
    "https://openalex.org/W652061993",
    "https://openalex.org/W915666225"
  ]
}