{
  "id": "https://openalex.org/W2950710435",
  "title": "Relative Impacts of Simultaneous Stressors on a Pelagic Marine Ecosystem",
  "abstract": "Climate change and fishing are two of the greatest anthropogenic stressors on marine ecosystems. We investigate the effects of these stressors on Hawaii's deep-set longline fishery for bigeye tuna (Thunnus obesus) and the ecosystem which supports it using a size-based food web model that incorporates individual species and captures the metabolic effects of rising ocean temperatures. We find that when fishing and climate change are examined individually, fishing is the greater stressor. This suggests that proactive fisheries management could be a particularly effective tool for mitigating anthropogenic stressors either by balancing or outweighing climate effects. However, modeling these stressors jointly shows that even large management changes cannot completely offset climate effects. Furthermore, when climate change and fishing are considered together, their effects are to some degree synergistic. Our results suggest that a decline in Hawaii's longline fishery yield may be inevitable. The effect of climate change on the ecosystem depends primarily upon the intensity of fishing mortality. Management measures which take this into account can both minimize fishery decline and support at least some level of ecosystem resilience.",
  "authors": [
    {
      "name": "Phoebe A. Woodworth‐Jefcoats"
    },
    {
      "name": "Julia L. Blanchard"
    },
    {
      "name": "Jeffrey C. Drazen"
    }
  ],
  "publication_year": 2019,
  "cited_by_count": 46,
  "primary_topic": "Marine and fisheries research",
  "subfield_topic": "Global and Planetary Change",
  "field_topic": "Environmental Science",
  "domain_topic": "Physical Sciences",
  "referenced_works": [
    "https://openalex.org/W1523166088",
    "https://openalex.org/W1543409689",
    "https://openalex.org/W1841065447",
    "https://openalex.org/W1912473322",
    "https://openalex.org/W1973831399",
    "https://openalex.org/W1982765705",
    "https://openalex.org/W1983827876",
    "https://openalex.org/W1984133743",
    "https://openalex.org/W1984415881",
    "https://openalex.org/W1992675871",
    "https://openalex.org/W1997065014",
    "https://openalex.org/W1998248183",
    "https://openalex.org/W2006666405",
    "https://openalex.org/W2007173289",
    "https://openalex.org/W2007942889",
    "https://openalex.org/W2013735779",
    "https://openalex.org/W2015403614",
    "https://openalex.org/W2016800147",
    "https://openalex.org/W2019020595",
    "https://openalex.org/W2024966118",
    "https://openalex.org/W2028787031",
    "https://openalex.org/W2029028922",
    "https://openalex.org/W2032357273",
    "https://openalex.org/W2032390643",
    "https://openalex.org/W2054534384",
    "https://openalex.org/W2059514316",
    "https://openalex.org/W2061580780",
    "https://openalex.org/W2068292608",
    "https://openalex.org/W2085539873",
    "https://openalex.org/W2096476151",
    "https://openalex.org/W2109492025",
    "https://openalex.org/W2109724904",
    "https://openalex.org/W2114795157",
    "https://openalex.org/W2119063528",
    "https://openalex.org/W2122974269",
    "https://openalex.org/W2130474435",
    "https://openalex.org/W2131988450",
    "https://openalex.org/W2132405265",
    "https://openalex.org/W2133762778",
    "https://openalex.org/W2136199724",
    "https://openalex.org/W2139585483",
    "https://openalex.org/W2142162210",
    "https://openalex.org/W2143147307",
    "https://openalex.org/W2143643595",
    "https://openalex.org/W2153905523",
    "https://openalex.org/W2155258266",
    "https://openalex.org/W2156505961",
    "https://openalex.org/W2157727063",
    "https://openalex.org/W2160497846",
    "https://openalex.org/W2167702433",
    "https://openalex.org/W2169757115",
    "https://openalex.org/W2193503481",
    "https://openalex.org/W2232267142",
    "https://openalex.org/W2290982036",
    "https://openalex.org/W2319346646",
    "https://openalex.org/W2513563772",
    "https://openalex.org/W2514963967",
    "https://openalex.org/W2541901302",
    "https://openalex.org/W2547178410",
    "https://openalex.org/W2563747423",
    "https://openalex.org/W2567277721",
    "https://openalex.org/W2577831312",
    "https://openalex.org/W2587262347",
    "https://openalex.org/W2606255265",
    "https://openalex.org/W2617753608",
    "https://openalex.org/W27623815",
    "https://openalex.org/W2762984108",
    "https://openalex.org/W2772043370",
    "https://openalex.org/W2790025691",
    "https://openalex.org/W2793797907",
    "https://openalex.org/W2804852872",
    "https://openalex.org/W2909795307",
    "https://openalex.org/W2917939479",
    "https://openalex.org/W2935904309",
    "https://openalex.org/W4245523148"
  ]
}